QcloudApi/__init__.py
QcloudApi/qcloudapi.py
QcloudApi/common/__init__.py
QcloudApi/common/api_exception.py
QcloudApi/common/request.py
QcloudApi/common/sign.py
QcloudApi/modules/__init__.py
QcloudApi/modules/account.py
QcloudApi/modules/apigateway.py
QcloudApi/modules/athena.py
QcloudApi/modules/base.py
QcloudApi/modules/batch.py
QcloudApi/modules/bgpip.py
QcloudApi/modules/bill.py
QcloudApi/modules/bm.py
QcloudApi/modules/bmeip.py
QcloudApi/modules/bmlb.py
QcloudApi/modules/bmvpc.py
QcloudApi/modules/cbs.py
QcloudApi/modules/ccr.py
QcloudApi/modules/ccs.py
QcloudApi/modules/cdb.py
QcloudApi/modules/cdn.py
QcloudApi/modules/cloudaudit.py
QcloudApi/modules/cmem.py
QcloudApi/modules/cns.py
QcloudApi/modules/cvm.py
QcloudApi/modules/dc.py
QcloudApi/modules/dfw.py
QcloudApi/modules/eip.py
QcloudApi/modules/emr.py
QcloudApi/modules/feecenter.py
QcloudApi/modules/image.py
QcloudApi/modules/lb.py
QcloudApi/modules/live.py
QcloudApi/modules/market.py
QcloudApi/modules/monitor.py
QcloudApi/modules/partners.py
QcloudApi/modules/redis.py
QcloudApi/modules/scaling.py
QcloudApi/modules/scf.py
QcloudApi/modules/sec.py
QcloudApi/modules/snapshot.py
QcloudApi/modules/sts.py
QcloudApi/modules/tbaas.py
QcloudApi/modules/tdsql.py
QcloudApi/modules/tmt.py
QcloudApi/modules/trade.py
QcloudApi/modules/vod.py
QcloudApi/modules/vpc.py
QcloudApi/modules/wenzhi.py
QcloudApi/modules/yunsou.py
async_timeout/__init__.py
bson/__init__.py
bson/_helpers.py
bson/binary.py
bson/code.py
bson/codec_options.py
bson/dbref.py
bson/decimal128.py
bson/errors.py
bson/int64.py
bson/json_util.py
bson/max_key.py
bson/min_key.py
bson/objectid.py
bson/raw_bson.py
bson/regex.py
bson/son.py
bson/timestamp.py
bson/tz_util.py
certifi/__init__.py
certifi/__main__.py
certifi/core.py
charset_normalizer/__init__.py
charset_normalizer/api.py
charset_normalizer/cd.py
charset_normalizer/constant.py
charset_normalizer/legacy.py
charset_normalizer/md.py
charset_normalizer/models.py
charset_normalizer/utils.py
py_base_layer-1.0.0.dist-info/METADATA
py_base_layer-1.0.0.dist-info/WHEEL
py_base_layer-1.0.0.dist-info/top_level.txt
py_base_layer-1.0.0.dist-info/RECORD
